psychopy_glfw/__init__.py
psychopy_glfw/glfwbackend.py
psychopy_glfw-0.0.2.dist-info/LICENSE
psychopy_glfw-0.0.2.dist-info/METADATA
psychopy_glfw-0.0.2.dist-info/WHEEL
psychopy_glfw-0.0.2.dist-info/entry_points.txt
psychopy_glfw-0.0.2.dist-info/top_level.txt
psychopy_glfw-0.0.2.dist-info/RECORD
